amaranth-stubs/__init__.pyi
amaranth-stubs/_unused.pyi
amaranth-stubs/_utils.pyi
amaranth-stubs/asserts.pyi
amaranth-stubs/tracer.pyi
amaranth-stubs/utils.pyi
amaranth-stubs/_toolchain/yosys.pyi
amaranth-stubs/back/__init__.pyi
amaranth-stubs/back/verilog.pyi
amaranth-stubs/build/__init__.pyi
amaranth-stubs/build/dsl.pyi
amaranth-stubs/build/plat.pyi
amaranth-stubs/build/res.pyi
amaranth-stubs/build/run.pyi
amaranth-stubs/hdl/__init__.pyi
amaranth-stubs/hdl/_ast.pyi
amaranth-stubs/hdl/_cd.pyi
amaranth-stubs/hdl/_dsl.pyi
amaranth-stubs/hdl/_ir.pyi
amaranth-stubs/hdl/_mem.pyi
amaranth-stubs/hdl/_nir.pyi
amaranth-stubs/hdl/_xfrm.pyi
amaranth-stubs/hdl/rec.pyi
amaranth-stubs/lib/data.pyi
amaranth-stubs/lib/enum.pyi
amaranth-stubs/lib/fifo.pyi
amaranth-stubs/lib/io.pyi
amaranth-stubs/lib/memory.pyi
amaranth-stubs/lib/meta.pyi
amaranth-stubs/lib/scheduler.pyi
amaranth-stubs/lib/stream.pyi
amaranth-stubs/lib/wiring.pyi
amaranth-stubs/sim/__init__.pyi
amaranth-stubs/sim/_async.pyi
amaranth-stubs/sim/_base.pyi
amaranth-stubs/sim/_pycoro.pyi
amaranth-stubs/sim/core.pyi
amaranth-stubs/sim/pysim.pyi
amaranth-stubs/vendor/__init__.pyi
amaranth-stubs/vendor/_lattice_ecp5.pyi
amaranth-stubs/vendor/_lattice_ice40.pyi
amaranth_stubs-0.1.1.dist-info/licenses/LICENSE
amaranth_types/__init__.py
amaranth_types/memory.py
amaranth_types/types.py
amaranth_stubs-0.1.1.dist-info/METADATA
amaranth_stubs-0.1.1.dist-info/WHEEL
amaranth_stubs-0.1.1.dist-info/top_level.txt
amaranth_stubs-0.1.1.dist-info/RECORD
